dishka_strawberry/__init__.py
dishka_strawberry/fastapi.py
dishka_strawberry-0.2.0.dist-info/METADATA
dishka_strawberry-0.2.0.dist-info/WHEEL
dishka_strawberry-0.2.0.dist-info/licenses/LICENSE
dishka_strawberry-0.2.0.dist-info/RECORD
