Metadata-Version: 2.4
Name: dishka-strawberry
Version: 0.2.0
Summary: Dishka integration for Strawberry
Project-URL: Source, https://github.com/aryadovoy/dishka-strawberry
Author-email: Andrey Ryadovoy <ryav.omsk@gmail.com>
License-Expression: Apache-2.0
License-File: LICENSE
Classifier: Intended Audience :: Developers
Classifier: Operating System :: OS Independent
Classifier: Programming Language :: Python :: 3.10
Classifier: Programming Language :: Python :: 3.11
Classifier: Programming Language :: Python :: 3.12
Classifier: Programming Language :: Python :: 3.13
Classifier: Programming Language :: Python :: 3.14
Classifier: Topic :: Software Development :: Libraries
Classifier: Typing :: Typed
Requires-Python: >=3.10
Requires-Dist: dishka>=1.4.0
Requires-Dist: strawberry-graphql>=0.263.0
